{"character": "ぬ", "strokes": [[{"x": 173, "y": 119, "pressure": 0.5, "timestamp": 158797}, {"x": 168, "y": 128.5, "pressure": 0.5, "timestamp": 158847}, {"x": 168, "y": 128.5, "pressure": 0.5, "timestamp": 158847}, {"x": 168.5, "y": 151.5, "pressure": 0.5, "timestamp": 158863}, {"x": 170.5, "y": 166, "pressure": 0.5, "timestamp": 158872}, {"x": 173, "y": 182.5, "pressure": 0.5, "timestamp": 158880}, {"x": 180.5, "y": 218, "pressure": 0.5, "timestamp": 158897}, {"x": 191.5, "y": 254.5, "pressure": 0.5, "timestamp": 158913}, {"x": 207, "y": 288.5, "pressure": 0.5, "timestamp": 158930}, {"x": 221.5, "y": 315.5, "pressure": 0.5, "timestamp": 158946}, {"x": 236, "y": 334, "pressure": 0.5, "timestamp": 158963}, {"x": 250, "y": 347, "pressure": 0.5, "timestamp": 158980}, {"x": 262, "y": 351.5, "pressure": 0.5, "timestamp": 158996}], [{"x": 293.5, "y": 135.5, "pressure": 0.5, "timestamp": 159238}, {"x": 285, "y": 137.5, "pressure": 0.5, "timestamp": 159280}, {"x": 285, "y": 137.5, "pressure": 0.5, "timestamp": 159280}, {"x": 280.5, "y": 154, "pressure": 0.5, "timestamp": 159296}, {"x": 277, "y": 166, "pressure": 0.5, "timestamp": 159305}, {"x": 272.5, "y": 178.5, "pressure": 0.5, "timestamp": 159313.00000000003}, {"x": 262, "y": 206, "pressure": 0.5, "timestamp": 159330}, {"x": 249, "y": 234, "pressure": 0.5, "timestamp": 159346}, {"x": 234.5, "y": 264, "pressure": 0.5, "timestamp": 159363}, {"x": 218.5, "y": 293, "pressure": 0.5, "timestamp": 159380}, {"x": 203, "y": 316.5, "pressure": 0.5, "timestamp": 159396.00000000003}, {"x": 188.5, "y": 333.5, "pressure": 0.5, "timestamp": 159413}, {"x": 175.5, "y": 346.5, "pressure": 0.5, "timestamp": 159430}, {"x": 163.5, "y": 354, "pressure": 0.5, "timestamp": 159446}, {"x": 151.5, "y": 359, "pressure": 0.5, "timestamp": 159463}, {"x": 142, "y": 359.5, "pressure": 0.5, "timestamp": 159480}, {"x": 134.5, "y": 355, "pressure": 0.5, "timestamp": 159496}, {"x": 130, "y": 344, "pressure": 0.5, "timestamp": 159513}, {"x": 129.5, "y": 328.5, "pressure": 0.5, "timestamp": 159530}, {"x": 131.5, "y": 312.5, "pressure": 0.5, "timestamp": 159546}, {"x": 142, "y": 290, "pressure": 0.5, "timestamp": 159563.00000000003}, {"x": 159, "y": 264, "pressure": 0.5, "timestamp": 159580}, {"x": 180.5, "y": 238.5, "pressure": 0.5, "timestamp": 159596}, {"x": 205, "y": 217, "pressure": 0.5, "timestamp": 159613}, {"x": 233, "y": 200.5, "pressure": 0.5, "timestamp": 159630}, {"x": 261.5, "y": 187, "pressure": 0.5, "timestamp": 159646.00000000003}, {"x": 289.5, "y": 178.5, "pressure": 0.5, "timestamp": 159663}, {"x": 315.5, "y": 174, "pressure": 0.5, "timestamp": 159680}, {"x": 336.5, "y": 173.5, "pressure": 0.5, "timestamp": 159696}, {"x": 353, "y": 181, "pressure": 0.5, "timestamp": 159713}, {"x": 365.5, "y": 192.5, "pressure": 0.5, "timestamp": 159730}, {"x": 373.5, "y": 209, "pressure": 0.5, "timestamp": 159746}, {"x": 378.5, "y": 228.5, "pressure": 0.5, "timestamp": 159763}, {"x": 379, "y": 252.5, "pressure": 0.5, "timestamp": 159780}, {"x": 379, "y": 279.5, "pressure": 0.5, "timestamp": 159796}, {"x": 374.5, "y": 305, "pressure": 0.5, "timestamp": 159813.00000000003}, {"x": 368.5, "y": 325, "pressure": 0.5, "timestamp": 159830}, {"x": 361.5, "y": 342.5, "pressure": 0.5, "timestamp": 159846}, {"x": 354, "y": 353.5, "pressure": 0.5, "timestamp": 159863}, {"x": 347, "y": 359, "pressure": 0.5, "timestamp": 159880}, {"x": 339.5, "y": 360, "pressure": 0.5, "timestamp": 159896.00000000003}, {"x": 331.5, "y": 357, "pressure": 0.5, "timestamp": 159913}, {"x": 323, "y": 347, "pressure": 0.5, "timestamp": 159929}, {"x": 317, "y": 332.5, "pressure": 0.5, "timestamp": 159946}, {"x": 313, "y": 316, "pressure": 0.5, "timestamp": 159963}, {"x": 311.5, "y": 303.5, "pressure": 0.5, "timestamp": 159980}, {"x": 311.5, "y": 294.5, "pressure": 0.5, "timestamp": 159996}, {"x": 317, "y": 289, "pressure": 0.5, "timestamp": 160013}, {"x": 325, "y": 285.5, "pressure": 0.5, "timestamp": 160030}, {"x": 335, "y": 283, "pressure": 0.5, "timestamp": 160046}, {"x": 346.5, "y": 283, "pressure": 0.5, "timestamp": 160063.00000000003}, {"x": 358.5, "y": 288.5, "pressure": 0.5, "timestamp": 160079}, {"x": 371, "y": 295, "pressure": 0.5, "timestamp": 160096}, {"x": 382, "y": 301.5, "pressure": 0.5, "timestamp": 160113}, {"x": 390, "y": 306.5, "pressure": 0.5, "timestamp": 160129}, {"x": 395, "y": 309, "pressure": 0.5, "timestamp": 160146.00000000003}, {"x": 395.5, "y": 309, "pressure": 0.5, "timestamp": 160154}]], "metadata": {}}